dialogs_framework/__init__.py
dialogs_framework/async_gen_dialogs.py
dialogs_framework/dialog_state.py
dialogs_framework/dialogs.py
dialogs_framework/fallback_dialog.py
dialogs_framework/gen_dialogs.py
dialogs_framework/generic_types.py
dialogs_framework/message_queue.py
dialogs_framework/persistence/__init__.py
dialogs_framework/persistence/in_memory.py
dialogs_framework/persistence/persistence.py
dialogs_framework/types.py
dialogs_framework-0.2.1.dist-info/WHEEL
dialogs_framework-0.2.1.dist-info/METADATA
dialogs_framework-0.2.1.dist-info/RECORD
