Metadata-Version: 2.1
Name: dialogs-framework
Version: 0.2.1
Summary: 
Author: Alon
Author-email: alon.gal@khealth.com
Requires-Python: >=3.7,<4.0
Classifier: Programming Language :: Python :: 3
Classifier: Programming Language :: Python :: 3.10
Classifier: Programming Language :: Python :: 3.7
Classifier: Programming Language :: Python :: 3.8
Classifier: Programming Language :: Python :: 3.9
Requires-Dist: contextvars (>=2.4,<3.0)
